dsaedge/__init__.py
dsaedge/advanced_data_structures/__init__.py
dsaedge/advanced_data_structures/disjoint_set_union.py
dsaedge/advanced_data_structures/fenwick_tree.py
dsaedge/advanced_data_structures/segment_tree.py
dsaedge/advanced_data_structures/trie.py
dsaedge/algorithmic_paradigms/__init__.py
dsaedge/algorithmic_paradigms/kmp_search.py
dsaedge/algorithmic_paradigms/knapsack_problem.py
dsaedge/algorithmic_paradigms/longest_common_subsequence.py
dsaedge/algorithmic_paradigms/n_queens.py
dsaedge/algorithmic_paradigms/sudoku_solver.py
dsaedge/graphs/__init__.py
dsaedge/graphs/bellman_ford.py
dsaedge/graphs/floyd_warshall.py
dsaedge/graphs/graph_representation.py
dsaedge/graphs/kruskal_algorithm.py
dsaedge/graphs/topological_sort.py
dsaedge/hash_tables/__init__.py
dsaedge/hash_tables/hash_table.py
dsaedge/heaps/__init__.py
dsaedge/heaps/min_heap.py
dsaedge/linked_lists/__init__.py
dsaedge/linked_lists/circular_doubly_linked_list.py
dsaedge/linked_lists/circular_singly_linked_list.py
dsaedge/linked_lists/doubly_linked_list.py
dsaedge/linked_lists/singly_linked_list.py
dsaedge/searching/__init__.py
dsaedge/searching/searching_algorithms.py
dsaedge/sorting/__init__.py
dsaedge/sorting/bubble_sort.py
dsaedge/sorting/heap_sort.py
dsaedge/sorting/insertion_sort.py
dsaedge/sorting/merge_sort.py
dsaedge/sorting/quick_sort.py
dsaedge/sorting/selection_sort.py
dsaedge/trees/__init__.py
dsaedge/trees/avl_tree.py
dsaedge/trees/binary_search_tree.py
dsaedge/trees/binary_tree.py
dsaedge-0.4.0.dist-info/licenses/LICENSE
dsaedge-0.4.0.dist-info/METADATA
dsaedge-0.4.0.dist-info/WHEEL
dsaedge-0.4.0.dist-info/top_level.txt
dsaedge-0.4.0.dist-info/RECORD
